MANIFEST.in
setup.cfg
setup.py
garlicsim_lib/__init__.py
garlicsim_lib/lgpl2.1_license.txt
garlicsim_lib/simpacks/__init__.py
garlicsim_lib/simpacks/_endable_life_test/__init__.py
garlicsim_lib/simpacks/_endable_life_test/settings.py
garlicsim_lib/simpacks/_endable_life_test/state.py
garlicsim_lib/simpacks/_history_test/__init__.py
garlicsim_lib/simpacks/_history_test/state.py
garlicsim_lib/simpacks/_prisoner_persistent_test/__init__.py
garlicsim_lib/simpacks/_prisoner_persistent_test/base_player.py
garlicsim_lib/simpacks/_prisoner_persistent_test/player_type.py
garlicsim_lib/simpacks/_prisoner_persistent_test/settings.py
garlicsim_lib/simpacks/_prisoner_persistent_test/state.py
garlicsim_lib/simpacks/_prisoner_persistent_test/players/__init__.py
garlicsim_lib/simpacks/_prisoner_persistent_test/players/angel.py
garlicsim_lib/simpacks/_prisoner_persistent_test/players/devil.py
garlicsim_lib/simpacks/_prisoner_persistent_test/players/tit_for_tat.py
garlicsim_lib/simpacks/life/__init__.py
garlicsim_lib/simpacks/life/settings.py
garlicsim_lib/simpacks/life/state.py
garlicsim_lib/simpacks/prisoner/__init__.py
garlicsim_lib/simpacks/prisoner/base_player.py
garlicsim_lib/simpacks/prisoner/player_type.py
garlicsim_lib/simpacks/prisoner/settings.py
garlicsim_lib/simpacks/prisoner/state.py
garlicsim_lib/simpacks/prisoner/players/__init__.py
garlicsim_lib/simpacks/prisoner/players/angel.py
garlicsim_lib/simpacks/prisoner/players/devil.py
garlicsim_lib/simpacks/prisoner/players/tit_for_tat.py
garlicsim_lib/simpacks/queue/__init__.py
garlicsim_lib/simpacks/queue/client.py
garlicsim_lib/simpacks/queue/facility.py
garlicsim_lib/simpacks/queue/math_tools.py
garlicsim_lib/simpacks/queue/population.py
garlicsim_lib/simpacks/queue/server.py
garlicsim_lib/simpacks/queue/settings.py
garlicsim_lib/simpacks/queue/state.py
garlicsim_lib/simpacks/queue/events/__init__.py
garlicsim_lib/simpacks/queue/events/event.py
garlicsim_lib/simpacks/queue/events/event_set.py
garlicsim_lib_py3.egg-info/PKG-INFO
garlicsim_lib_py3.egg-info/SOURCES.txt
garlicsim_lib_py3.egg-info/dependency_links.txt
garlicsim_lib_py3.egg-info/not-zip-safe
garlicsim_lib_py3.egg-info/requires.txt
garlicsim_lib_py3.egg-info/top_level.txt
